{"usage": {"text_units": 1, "text_characters": 2788, "features": 5}, "sentiment": {"document": {"score": 0.523185, "label": "positive"}}, "language": "en", "keywords": [{"text": "quality control department", "relevance": 0.923686}, {"text": "inspection report", "relevance": 0.889764}, {"text": "quality supervision department", "relevance": 0.678258}, {"text": "inspection report form", "relevance": 0.673746}, {"text": "finished product inspection", "relevance": 0.594382}, {"text": "unqualified product management", "relevance": 0.510276}, {"text": "GMP certification", "relevance": 0.463456}, {"text": "intermediate product management", "relevance": 0.461423}, {"text": "red substandard product", "relevance": 0.433913}, {"text": "product inspection report", "relevance": 0.423226}, {"text": "GMP certification products", "relevance": 0.42001}, {"text": "cross-quality control department", "relevance": 0.417938}, {"text": "substandard products", "relevance": 0.408356}, {"text": "workshop", "relevance": 0.399002}, {"text": "intermediate products", "relevance": 0.397511}, {"text": "batch number", "relevance": 0.396869}, {"text": "control department sampling", "relevance": 0.396632}, {"text": "inspection report report", "relevance": 0.395848}, {"text": "supervision department audit", "relevance": 0.384868}, {"text": "production technology department", "relevance": 0.366582}, {"text": "factory technical person", "relevance": 0.341895}, {"text": "unqualified products", "relevance": 0.321834}, {"text": "unqualified item", "relevance": 0.290514}, {"text": "packaging products", "relevance": 0.233502}, {"text": "nonconforming product", "relevance": 0.229866}, {"text": "production date", "relevance": 0.223483}, {"text": "packaging process", "relevance": 0.209372}, {"text": "analysis report", "relevance": 0.209017}, {"text": "responsible department", "relevance": 0.208723}, {"text": "finished goods", "relevance": 0.204362}, {"text": "following principles", "relevance": 0.202364}], "entities": [{"type": "JobTitle", "text": "Quality Supervision Department", "relevance": 0.773136, "count": 1}, {"type": "JobTitle", "text": "supervisor", "relevance": 0.522066, "count": 2}], "concepts": [{"text": "Quality control", "relevance": 0.93569, "dbpedia_resource": "http://dbpedia.org/resource/Quality_control"}, {"text": "Manufacturing", "relevance": 0.902884, "dbpedia_resource": "http://dbpedia.org/resource/Manufacturing"}, {"text": "Management", "relevance": 0.813079, "dbpedia_resource": "http://dbpedia.org/resource/Management"}, {"text": "Product management", "relevance": 0.706674, "dbpedia_resource": "http://dbpedia.org/resource/Product_management"}, {"text": "Warehouse", "relevance": 0.682346, "dbpedia_resource": "http://dbpedia.org/resource/Warehouse"}, {"text": "Grammatical number", "relevance": 0.628316, "dbpedia_resource": "http://dbpedia.org/resource/Grammatical_number"}, {"text": "Production and manufacturing", "relevance": 0.579253, "dbpedia_resource": "http://dbpedia.org/resource/Production_and_manufacturing"}, {"text": "Intermediate good", "relevance": 0.570679, "dbpedia_resource": "http://dbpedia.org/resource/Intermediate_good"}], "categories": [{"score": 0.448901, "label": "/business and industrial/business operations/business plans"}, {"score": 0.432135, "label": "/law, govt and politics/politics/elections"}, {"score": 0.15714, "label": "/business and industrial/manufacturing"}]}